LICENSE
README.md
setup.py
FrameNet/Frame.py
FrameNet/FrameElement.py
FrameNet/FrameElementList.py
FrameNet/FrameNet.py
FrameNet/__init__.py
FrameNet/data/__init__.py
FrameNet/data/framenet.xml
NlpToolkit_FrameNet.egg-info/PKG-INFO
NlpToolkit_FrameNet.egg-info/SOURCES.txt
NlpToolkit_FrameNet.egg-info/dependency_links.txt
NlpToolkit_FrameNet.egg-info/top_level.txt