Metadata-Version: 2.1
Name: NlpToolkit-FrameNet
Version: 1.0.10
Summary: FrameNet library
Home-page: https://github.com/StarlangSoftware/TurkishFrameNet-Py
Author: olcaytaner
Author-email: olcay.yildiz@ozyegin.edu.tr
License: UNKNOWN
Platform: UNKNOWN
